54.14 字符串
54.14.1 第一个例子

字符串也是对象，和其他对象的构造方式相同。（还有数组）


    public static void main(String[] args)
    {
    System.out.println("What is your name?");
    String input = System.console().readLine();
    System.out.println("Hello, "+input);
    }
    public static void main(java.lang.String[]);
    flags: ACC_PUBLIC, ACC_STATIC
    Code:
    stack=3, locals=2, args_size=1
    0: getstatic #2 // Field java/⤦
    Ç lang/System.out:Ljava/io/PrintStream;
    3: ldc #3 // String What is⤦
    Ç your name?
    5: invokevirtual #4 // Method java/io⤦
    Ç /PrintStream.println:(Ljava/lang/String;)V
    8: invokestatic #5 // Method java/⤦
    Ç lang/System.console:()Ljava/io/Console;
    11: invokevirtual #6 // Method java/io⤦
    Ç /Console.readLine:()Ljava/lang/String;
    14: astore_1
    15: getstatic #2 // Field java/⤦
    Ç lang/System.out:Ljava/io/PrintStream;
    18: new #7 // class java/⤦
    Ç lang/StringBuilder
    21: dup
    22: invokespecial #8 // Method java/⤦
    Ç lang/StringBuilder."<init>":()V
    25: ldc #9 // String Hello,
    27: invokevirtual #10 // Method java/⤦
    Ç lang/StringBuilder.append:(Ljava/lang/String;)Ljava/lang/⤦
    Ç StringBuilder;
    30: aload_1
    31: invokevirtual #10 // Method java/⤦
    Ç lang/StringBuilder.append:(Ljava/lang/String;)Ljava/lang/⤦
    Ç StringBuilder;
    34: invokevirtual #11 // Method java/⤦
    Ç lang/StringBuilder.toString:()Ljava/lang/String;
    37: invokevirtual #4 // Method java/io⤦
    Ç /PrintStream.println:(Ljava/lang/String;)V
    40: return

944
在11行偏移调用了readline()方法，字符串引用（由用户提供）被存储在栈顶，在14行偏移,字符串引用被存储在LVA的1号槽中。


用户输入的字符串在30行偏移处重新加载并和 “hello”字符进行了链接，使用的是StringBulder类，在17行偏移,构造的字符串被pirntln方法打印。

54.14.2 第二个例子
另外一个例子

    public class strings
    {
    public static char test (String a)
    {
    return a.charAt(3);
    };
    public static String concat (String a, String b)
    {
    return a+b;
    }
    }
    public static char test(java.lang.String);
    flags: ACC_PUBLIC, ACC_STATIC
    Code:
    stack=2, locals=1, args_size=1
    0: aload_0
    1: iconst_3
    2: invokevirtual #2 // Method java/⤦
    Ç lang/String.charAt:(I)C
    5: ireturn

945

字符串的链接使用用StringBuilder类完成。


    public static java.lang.String concat(java.lang.String, java.⤦
    Ç lang.String);
    flags: ACC_PUBLIC, ACC_STATIC
    Code:
    stack=2, locals=2, args_size=2
    0: new #3 // class java/⤦
    Ç lang/StringBuilder
    3: dup
    4: invokespecial #4 // Method java/⤦
    Ç lang/StringBuilder."<init>":()V
    7: aload_0
    8: invokevirtual #5 // Method java/⤦
    Ç lang/StringBuilder.append:(Ljava/lang/String;)Ljava/lang/⤦
    Ç StringBuilder;
    11: aload_1
    12: invokevirtual #5 // Method java/⤦
    Ç lang/StringBuilder.append:(Ljava/lang/String;)Ljava/lang/⤦
    Ç StringBuilder;
    15: invokevirtual #6 // Method java/⤦
    Ç lang/StringBuilder.toString:()Ljava/lang/String;
    18: areturn

另外一个例子
    
    public static void main(String[] args)
    {
    String s="Hello!";
    int n=123;
    System.out.println("s=" + s + " n=" + n);
    }

字符串构造用StringBuilder类，和它的添加方法，被构造的字符串被传递给println方法。

    
    public static void main(java.lang.String[]);
    flags: ACC_PUBLIC, ACC_STATIC
    Code:
    stack=3, locals=3, args_size=1
    0: ldc #2 // String Hello!
    2: astore_1
    3: bipush 123
    5: istore_2
    6: getstatic #3 // Field java/⤦
    Ç lang/System.out:Ljava/io/PrintStream;
    9: new #4 // class java/⤦
    Ç lang/StringBuilder
    12: dup
    13: invokespecial #5 // Method java/⤦
    Ç lang/StringBuilder."<init>":()V
    16: ldc #6 // String s=
    18: invokevirtual #7 // Method java/⤦
    Ç lang/StringBuilder.append:(Ljava/lang/String;)Ljava/lang/⤦
    Ç StringBuilder;
    21: aload_1
    22: invokevirtual #7 // Method java/⤦
    Ç lang/StringBuilder.append:(Ljava/lang/String;)Ljava/lang/⤦
    Ç StringBuilder;
    25: ldc #8 // String n=
    27: invokevirtual #7 // Method java/⤦
    Ç lang/StringBuilder.append:(Ljava/lang/String;)Ljava/lang/⤦
    Ç StringBuilder;
    30: iload_2
    31: invokevirtual #9 // Method java/⤦
    Ç lang/StringBuilder.append:(I)Ljava/lang/StringBuilder;
    34: invokevirtual #10 // Method java/⤦
    Ç lang/StringBuilder.toString:()Ljava/lang/String;
    37: invokevirtual #11 // Method java/io⤦
    Ç /PrintStream.println:(Ljava/lang/String;)V
    40: return


 946

