54.5 简单的函数调用
mathrandom()返回一个伪随机数，函数范围在「0.0...1.0)之间，但对我们来说，由于一些原因，我们常常需要设计一个函数返回数值范围在「0.0...0.5)


    public class HalfRandom
    {
    public static double f()
    {
    return Math.random()/2;
    }
    }
    


54.8 常量区

    ...
    #2 = Methodref #18.#19 // java/lang/Math.⤦
    Ç random:()D
    6(Java) Local Variable Array
    
    #3 = Double 2.0d
    ...
    #12 = Utf8 ()D
    ...
    #18 = Class #22 // java/lang/Math
    #19 = NameAndType #23:#12 // random:()D
    #22 = Utf8 java/lang/Math
    #23 = Utf8 random
    public static double f();
    flags: ACC_PUBLIC, ACC_STATIC
    Code:
    stack=4, locals=0, args_size=0
    0: invokestatic #2 // Method java/⤦
    Ç lang/Math.random:()D
    3: ldc2_w #3 // double 2.0d
    6: ddiv
    7: dreturn

java本地变量数组
916
静态执行调用math.random()函数，返回值在栈顶。结果是被0.5初返回的，但函数名是怎么被编码的呢？
在常量区使用methodres表达式,进行编码的，它定义类和方法的名称。第一个methodref 字段指向表达式，其次，指向通常文本字符（"java/lang/math"）
第二个methodref表达指向名字和类型表达式，同时链接两个字符。第一个方法的名字式字符串"random",第二个字符串是"()D",来编码函数类型，它以为这两个值（因此D是字符串）这种方式1JVM可以检查数据类型的正确性：2）java反编译器可以从被编译的类文件中修改数据类型。

最后，我们试着使用"hello，world！"作为例子。

    public class HelloWorld
    {
    public static void main(String[] args)
    {
    System.out.println("Hello, World");
    }
    }


54.9 常量区


917
常量区的ldc行偏移3，指向"hello，world！"字符串，并且将其入栈，在java里它被成为饮用，其实它就是指针，或是地址。

918

    ...
    #2 = Fieldref #16.#17 // java/lang/System.⤦
    Ç out:Ljava/io/PrintStream;
    #3 = String #18 // Hello, World
    #4 = Methodref #19.#20 // java/io/⤦
    Ç PrintStream.println:(Ljava/lang/String;)V
    ...
    #16 = Class #23 // java/lang/System
    #17 = NameAndType #24:#25 // out:Ljava/io/⤦
    Ç PrintStream;
    #18 = Utf8 Hello, World
    #19 = Class #26 // java/io/⤦
    Ç PrintStream
    #20 = NameAndType #27:#28 // println:(Ljava/⤦
    Ç lang/String;)V
    ...
    #23 = Utf8 java/lang/System
    #24 = Utf8 out
    #25 = Utf8 Ljava/io/PrintStream;
    #26 = Utf8 java/io/PrintStream
    #27 = Utf8 println
    #28 = Utf8 (Ljava/lang/String;)V
    ...
    public static void main(java.lang.String[]);
    flags: ACC_PUBLIC, ACC_STATIC
    Code:
    stack=2, locals=1, args_size=1
    0: getstatic #2 // Field java/⤦
    Ç lang/System.out:Ljava/io/PrintStream;
    3: ldc #3 // String Hello, ⤦
    Ç World
    5: invokevirtual #4 // Method java/io⤦
    Ç /PrintStream.println:(Ljava/lang/String;)V
    8: return

常见的invokevirtual指令，从常量区取信息，然后调用pringln()方法，貌似我们知道的println()方法，适用于各种数据类型，我这种println()函数版本，预先给的是字符串类型。

但是第一个getstatic指令是干什么的？这条指令取得对象信息的字段的一个引用或是地址。输出并将其进栈，这个值实际更像是println放的指针，因此，内部的print method取得两个参数，输入1指向对象的this指针，2）"hello，world"字符串的地址，确实，println()在被初始化系统的调用，对象之外，为了方便，javap使用工具把所有的信息都写入到注释中。

