54.8 条件跳转
让我们进入条件跳转

    public class abs
    {
    public static int abs(int a)
    {
    if (a<0)
    return -a;
    return a;
    }
    }
    public static int abs(int);
    flags: ACC_PUBLIC, ACC_STATIC
    Code:
    stack=1, locals=1, args_size=1
    0: iload_0
    1: ifge 7
    4: iload_0
    5: ineg
    6: ireturn
    7: iload_0
    8: ireturn

921

ifge跳转到7行偏移，如果栈顶的值大于等于0，别忘了，任何IFXX指令从栈中pop出栈值（用于进行比较）

另外一个例子

    public static int min (int a, int b)
    {
    if (a>b)
    return b;
    return a;
    }


我们得到的是：

    public static int min(int, int);
    flags: ACC_PUBLIC, ACC_STATIC
    Code:
    stack=2, locals=2, args_size=2
    0: iload_0
    1: iload_1
    2: if_icmple 7
    5: iload_1
    6: ireturn
    7: iload_0
    8: ireturn

if_icmple出栈两个值并比较他们，如果第三个子值比第一个值小（或者等于）发生跳转到行偏移7.

当我们定义max()函数。

    public static int max (int a, int b)
    {
    if (a>b)
    return a;
    return b;
    }

。。。结果代码是是一样的，但是最后两个iload指令（行偏移5和行偏移7）被跳转了。

    public static int max(int, int);
    flags: ACC_PUBLIC, ACC_STATIC
    Code:
    stack=2, locals=2, args_size=2
    0: iload_0
    1: iload_1
    2: if_icmple 7
    5: iload_0
    6: ireturn
    7: iload_1
    8: ireturn

922
更复杂的例子。。

    public class cond
    {
    public static void f(int i)
    {
    if (i<100)
    System.out.print("<100");
    if (i==100)
    System.out.print("==100");
    if (i>100)
    System.out.print(">100");
    if (i==0)
    System.out.print("==0");
    }
    }
    public static void f(int);
    flags: ACC_PUBLIC, ACC_STATIC
    Code:
    stack=2, locals=1, args_size=1
    0: iload_0
    1: bipush 100
    3: if_icmpge 14
    6: getstatic #2 // Field java/⤦
    Ç lang/System.out:Ljava/io/PrintStream;
    9: ldc #3 // String <100
    11: invokevirtual #4 // Method java/io⤦
    Ç /PrintStream.print:(Ljava/lang/String;)V
    14: iload_0
    15: bipush 100
    17: if_icmpne 28
    20: getstatic #2 // Field java/⤦
    Ç lang/System.out:Ljava/io/PrintStream;
    23: ldc #5 // String ==100
    25: invokevirtual #4 // Method java/io⤦
    Ç /PrintStream.print:(Ljava/lang/String;)V
    28: iload_0
    29: bipush 100
    31: if_icmple 42
    34: getstatic #2 // Field java/⤦
    Ç lang/System.out:Ljava/io/PrintStream;
    37: ldc #6 // String >100
    39: invokevirtual #4 // Method java/io⤦
    Ç /PrintStream.print:(Ljava/lang/String;)V
    42: iload_0
    43: ifne 54
    46: getstatic #2 // Field java/⤦
    Ç lang/System.out:Ljava/io/PrintStream;
    49: ldc #7 // String ==0
    51: invokevirtual #4 // Method java/io⤦
    Ç /PrintStream.print:(Ljava/lang/String;)V
    54: return
    
923
if_icmpge出栈两个值，并且比较它们，如果第的二个值大于第一个，发生跳转到行偏移14，if_icmpne和if_icmple做的工作类似，但是使用不同的判断条件。

在行偏移43的ifne指令，它的名字不是很恰当，我要愿意把它命名为ifnz

如果栈定的值不是0跳转，但是这是怎么做的，总跳转到行偏移54，如果输入的值不是另，如果是0，执行流程进入行偏移46，“==”字符串被打印。

N.BJVM没有无符号数据类型，所以，比较指令的操作数，只有还有符号整数值。

