54.16 类
简单类

清单 54.15: test.java
    
    public class test
    {
    public static int a;
    private static int b;
    public test()
    {
    a=0;
    b=0;
    }
    public static void set_a (int input)
    {
    a=input;
    }
    public static int get_a ()
    {
    return a;
    }
    public static void set_b (int input)
    {
    b=input;
    }
    public static int get_b ()
    {
    return b;
    }
    }

952

构造函数，设定两个字段0.

    public test();
    flags: ACC_PUBLIC
    Code:
    stack=1, locals=1, args_size=1
    0: aload_0
    1: invokespecial #1 // Method java/⤦
    Ç lang/Object."<init>":()V
    4: iconst_0
    5: putstatic #2 // Field a:I
    8: iconst_0
    9: putstatic #3 // Field b:I
    12: return

a的设定器

    public static void set_a(int);
    flags: ACC_PUBLIC, ACC_STATIC
    Code:
    stack=1, locals=1, args_size=1
    0: iload_0
    1: putstatic #2 // Field a:I
    4: return

a的取得器

    public static int get_a();
    flags: ACC_PUBLIC, ACC_STATIC
    Code:
    stack=1, locals=0, args_size=0
    0: getstatic #2 // Field a:I
    3: ireturn

b的设定器

    public static void set_b(int);
    flags: ACC_PUBLIC, ACC_STATIC
    Code:
    stack=1, locals=1, args_size=1
    0: iload_0
    1: putstatic #3 // Field b:I
    4: return

b的取得器

    public static int get_b();
    flags: ACC_PUBLIC, ACC_STATIC
    Code:
    stack=1, locals=0, args_size=0
    0: getstatic #3 // Field b:I
    3: ireturn


953
代码中的共有字段和实有字段工作恰来没有什么不同。 但是这里类型信息是在in.class 文件中，并且，无论如何它不可能访问私有字段。

让我们调用方法创建对象：
清单 54.16: ex1.java

954
新指令创建对象，但不调用构造函数（它在4行偏移被调用）set_a()方法被调用在16行偏移调用，一个字段访问使用getstatic指令。

    Listing 54.16: ex1.java
    public class ex1
    {
    public static void main(String[] args)
    {
    test obj=new test();
    obj.set_a (1234);
    System.out.println(obj.a);
    }
    }
    public static void main(java.lang.String[]);
    flags: ACC_PUBLIC, ACC_STATIC
    Code:
    stack=2, locals=2, args_size=1
    0: new #2 // class test
    3: dup
    4: invokespecial #3 // Method test."<⤦
    Ç init>":()V
    7: astore_1
    8: aload_1
    9: pop
    10: sipush 1234
    13: invokestatic #4 // Method test.⤦
    Ç set_a:(I)V
    16: getstatic #5 // Field java/⤦
    Ç lang/System.out:Ljava/io/PrintStream;
    19: aload_1
    20: pop
    21: getstatic #6 // Field test.a:I
    24: invokevirtual #7 // Method java/io⤦
    Ç /PrintStream.println:(I)V
    27: return

