54.11循环

    
    public class Loop
    {
    public static void main(String[] args)
    {
    for (int i = 1; i <= 10; i++)
    {
    System.out.println(i);
    }
    }
    }
    public static void main(java.lang.String[]);
    flags: ACC_PUBLIC, ACC_STATIC
    Code:
    stack=2, locals=2, args_size=1
    0: iconst_1
    1: istore_1
    2: iload_1
    3: bipush 10
    5: if_icmpgt 21
    8: getstatic #2 // Field java/⤦
    Ç lang/System.out:Ljava/io/PrintStream;
    11: iload_1
    12: invokevirtual #3 // Method java/io⤦
    Ç /PrintStream.println:(I)V
    15: iinc 1, 1
    18: goto 2
    21: return


icont_1将1推入到栈顶，istore_1将其存入到LVA的参数槽1，为什么没有零槽？因为main()函数只有一个参数，并且指向其的引用，就在第0号槽中。

因此，i本地变量总是在1号参数槽中。
指令在行3偏移和行5偏移，将i和10的比较。如果i大，执行流进入行21偏移，函数结束了，如果不被println调用。i在行11偏移进行了重新加载，之后给println使用。

多说一句，我们调用pringln打印数据类型是整型，我们看注释，“i，v”，i的意思是整型，v的意思是返回void。

当println函数结束，i是步进到行15偏移，指令第一个操作数是参数槽1的值。第二个是数值1与本地变量相加结果。

goto指令就是跳转，它跳转到循环体的开始地址，再行偏移2.

928页

让我们进行更复杂的例子。

    public class Fibonacci
    {
    public static void main(String[] args)
    {
    int limit = 20, f = 0, g = 1;
    for (int i = 1; i <= limit; i++)
    {
    f = f + g;
    g = f - g;
    System.out.println(f);
    }
    }
    }
    public static void main(java.lang.String[]);
    flags: ACC_PUBLIC, ACC_STATIC
    Code:
    stack=2, locals=5, args_size=1
    0: bipush 20
    2: istore_1
    3: iconst_0
    4: istore_2
    5: iconst_1
    6: istore_3
    7: iconst_1
    8: istore 4
    10: iload 4
    12: iload_1
    13: if_icmpgt 37
    16: iload_2
    17: iload_3
    18: iadd
    19: istore_2
    20: iload_2
    21: iload_3
    22: isub
    23: istore_3
    24: getstatic #2 // Field java/⤦
    Ç lang/System.out:Ljava/io/PrintStream;
    27: iload_2
    28: invokevirtual #3 // Method java/io⤦
    Ç /PrintStream.println:(I)V
    31: iinc 4, 1
    34: goto 10
    37: return



929
LVA槽中参数映射。
0-main（）的唯一参数。
1-限制，总是20.
2-f
3-g
4-i

我们可以看到java编译器在LVA参数槽分配变量，并且是相同的顺序，就像在源代码中声明变量。

分离指令istore，是用于访问参数槽0123，但是不能大于4，因此，附加一些操作，在行2，8偏移，使用槽中数据作为操作数，类似于在偏移10位置的iload指令。

无可口非，分离其他的槽，限制变量总是20（其本质上就是一个常数），重加载值很经常吗？

JVM JIT 编译器经常可以对其优化的很好。在代码中人工的干预优化其实是没有什么太大价值的。


